llm_mcp/__init__.py
llm_mcp/__main__.py
llm_mcp/manager.py
llm_mcp/plugin.py
llm_mcp/store.py
llm_mcp/cli/__init__.py
llm_mcp/cli/main.py
llm_mcp/cli/servers.py
llm_mcp/schema/__init__.py
llm_mcp/schema/parameters.py
llm_mcp/schema/servers.py
llm_mcp/transport/__init__.py
llm_mcp/transport/bg_runner.py
llm_mcp/transport/convert_tool.py
llm_mcp/transport/dispatch.py
llm_mcp/transport/http.py
llm_mcp/transport/stdio.py
llm_mcp/utils/__init__.py
llm_mcp/utils/convert_content.py
llm_mcp/utils/generate_server_name.py
llm_mcp/utils/parse_params.py
llm_mcp-0.0.2.dist-info/METADATA
llm_mcp-0.0.2.dist-info/WHEEL
llm_mcp-0.0.2.dist-info/entry_points.txt
llm_mcp-0.0.2.dist-info/licenses/LICENSE
llm_mcp-0.0.2.dist-info/RECORD
