Metadata-Version: 2.4
Name: llm-mcp
Version: 0.0.2
Summary: llm implementation of MCP for clients and servers.
Project-URL: Homepage, https://imaurer.github.io/llm-mcp/
Project-URL: Repository, https://github.com/imaurer/llm-mcp
Project-URL: Documentation, https://imaurer.github.io/llm-mcp/
Author-email: Ian Maurer <ian@genomoncology.com>
License-File: LICENSE
Keywords: python
Classifier: Intended Audience :: Developers
Classifier: Programming Language :: Python
Classifier: Programming Language :: Python :: 3
Classifier: Programming Language :: Python :: 3.10
Classifier: Programming Language :: Python :: 3.11
Classifier: Programming Language :: Python :: 3.12
Classifier: Programming Language :: Python :: 3.13
Classifier: Topic :: Software Development :: Libraries :: Python Modules
Requires-Python: <4.0,>=3.10
Requires-Dist: click>=8.2.0
Requires-Dist: llm==0.26
Requires-Dist: mcp[cli]>=1.9.0
Requires-Dist: pydantic>=2.11.4
